ragflow_mcp_server/__init__.py
ragflow_mcp_server/config.py
ragflow_mcp_server/server.py
ragflow_mcp_server-0.1.0.dist-info/METADATA
ragflow_mcp_server-0.1.0.dist-info/WHEEL
ragflow_mcp_server-0.1.0.dist-info/entry_points.txt
ragflow_mcp_server-0.1.0.dist-info/RECORD
